teasysnmp/__init__.py
teasysnmp/session.py
teasysnmp-0.6.dist-info/DESCRIPTION.rst
teasysnmp-0.6.dist-info/METADATA
teasysnmp-0.6.dist-info/RECORD
teasysnmp-0.6.dist-info/WHEEL
teasysnmp-0.6.dist-info/metadata.json
teasysnmp-0.6.dist-info/top_level.txt
